[
  {
    "title": "Ascensio",
    "description": "Ascensio is a comprehensive visual overhaul for Skyrim Anniversary Edition, providing very minimal gameplay tweaks in favor of an expansive graphical package that offers custom recolors and handpicked assets for a consistent visual experience.",
    "author": "Aljo, Bingus, and Curly",
    "maintainers": [
      "github/aljoxo",
      "github/bingusthecatto"
    ],
    "game": "skyrimspecialedition",
    "official": false,
    "tags": [
      "Anniversary Edition",
      "Visuals Only",
      "NeverNude"
    ],
    "nsfw": false,
    "utility_list": false,
    "image_contains_title": false,
    "force_down": false,
    "links": {
      "image": "https://raw.githubusercontent.com/Oghma-Infinium/Ascensio/main/Media/Ascensio%20WJ%20Banner.webp",
      "readme": "https://raw.githubusercontent.com/Oghma-Infinium/Ascensio/main/README.md",
      "download": "https://authored-files.wabbajack.org/Ascensio.wabbajack_a17ffa98-190e-4886-a94f-515edb2b80cf",
      "machineURL": "ascensio",
      "discordURL": "https://discord.gg/WakingDreams"
    },
    "download_metadata": {
      "Hash": "cRyFQHiJ31Y=",
      "Size": 119131030,
      "NumberOfArchives": 1095,
      "SizeOfArchives": 111399057852,
      "NumberOfInstalledFiles": 92540,
      "SizeOfInstalledFiles": 117684391173
    },
    "version": "1.1.1",
    "dateCreated": "2023-04-02T00:00:00",
    "dateUpdated": "2023-04-07T18:15:37.2964225Z",
    "repositoryName": ""
  },
  {
    "title": "Ascalon",
    "description": "Ascalon is a lightly modded list for Dragon\u0027s Dogma: Dark Arisen that also offers some customization for players.",
    "author": "Maelstrom",
    "maintainers": [
      "github/Maelstrom8"
    ],
    "game": "dragonsdogma",
    "official": false,
    "tags": [
      "Lite",
      "Educational",
      "They\u0027re Masterworks All You Can\u0027t Go Wrong"
    ],
    "nsfw": false,
    "utility_list": false,
    "image_contains_title": false,
    "force_down": false,
    "links": {
      "image": "https://raw.githubusercontent.com/Oghma-Infinium/Ascalon/main/Media/Ascalon.webp",
      "readme": "https://raw.githubusercontent.com/Oghma-Infinium/Ascalon/main/README.md",
      "download": "https://authored-files.wabbajack.org/Ascalon.wabbajack_f0e38228-b4b5-4b84-810f-434e0b4cd55e",
      "machineURL": "ascalon",
      "discordURL": "https://discord.gg/WakingDreams"
    },
    "download_metadata": {
      "Hash": "CG6b5/mBgmU=",
      "Size": 1662009,
      "NumberOfArchives": 1589,
      "SizeOfArchives": 15197695060,
      "NumberOfInstalledFiles": 4122,
      "SizeOfInstalledFiles": 15630879432
    },
    "version": "1.5.1",
    "dateCreated": "1970-01-01T00:00:00Z",
    "dateUpdated": "2023-04-04T05:35:48.6972729Z",
    "repositoryName": ""
  }
]